remote_ikernel-0.2.8.data/scripts/remote_ikernel
remote_ikernel/compat.py
remote_ikernel/__init__.py
remote_ikernel/manage.py
remote_ikernel/kernel.py
remote_ikernel/__main__.py
remote_ikernel-0.2.8.dist-info/DESCRIPTION.rst
remote_ikernel-0.2.8.dist-info/metadata.json
remote_ikernel-0.2.8.dist-info/top_level.txt
remote_ikernel-0.2.8.dist-info/RECORD
remote_ikernel-0.2.8.dist-info/WHEEL
remote_ikernel-0.2.8.dist-info/METADATA
