Metadata-Version: 2.0
Name: remote-ikernel
Version: 0.2.8
Summary: Running IPython kernels through batch queues
Home-page: https://bitbucket.org/tdaff/remote_ikernel
Author: Tom Daff
Author-email: tdd20@cam.ac.uk
License: BSD
Platform: UNKNOWN
Classifier: Programming Language :: Python :: 2
Classifier: Programming Language :: Python :: 3
Classifier: Framework :: IPython
Classifier: License :: OSI Approved :: BSD License
Requires-Dist: ipython
Requires-Dist: pexpect
